mylatextable/__init__.py
mylatextable/my_latex_table.py
mylatextable/my_long_table.py
mylatextable/my_table.py
mylatextable-0.0.3.dist-info/LICENSE
mylatextable-0.0.3.dist-info/METADATA
mylatextable-0.0.3.dist-info/WHEEL
mylatextable-0.0.3.dist-info/top_level.txt
mylatextable-0.0.3.dist-info/RECORD
