Metadata-Version: 2.2
Name: mylatextable
Version: 0.0.3
Summary: Quickly generate LaTeX tables
Author-email: Peter Robinson <peter.robinson@jax.org>
License: Copyright (c) 2023 Peter N. Robinson
Project-URL: homepage, https://github.com/pnrobinson/mylatextable
Project-URL: repository, https://github.com/pnrobinson/mylatextable.git
Project-URL: documentation, https://github.com/pnrobinson/mylatextable
Project-URL: bugtracker, https://github.com/pnrobinson/mylatextable/issues
Keywords: LaTeX,table
Classifier: License :: OSI Approved :: MIT License
Classifier: Operating System :: OS Independent
Classifier: Programming Language :: Python :: 3
Requires-Python: >=3.8
License-File: LICENSE
